<annotation>
	<folder>报纸</folder>
	<filename>IMG_20230922_182749.jpg</filename>
	<path>D:\Desktop\study\大四上\深度学习与应用综合实践\data\报纸\IMG_20230922_182749.jpg</path>
	<source>
		<database>Unknown</database>
	</source>
	<size>
		<width>2736</width>
		<height>3648</height>
		<depth>3</depth>
	</size>
	<segmented>0</segmented>
	<object>
		<name>Text</name>
		<pose>Unspecified</pose>
		<truncated>0</truncated>
		<difficult>0</difficult>
		<bndbox>
			<xmin>474</xmin>
			<ymin>104</ymin>
			<xmax>1670</xmax>
			<ymax>192</ymax>
		</bndbox>
	</object>
	<object>
		<name>Text</name>
		<pose>Unspecified</pose>
		<truncated>0</truncated>
		<difficult>0</difficult>
		<bndbox>
			<xmin>306</xmin>
			<ymin>184</ymin>
			<xmax>1818</xmax>
			<ymax>352</ymax>
		</bndbox>
	</object>
	<object>
		<name>Text</name>
		<pose>Unspecified</pose>
		<truncated>0</truncated>
		<difficult>0</difficult>
		<bndbox>
			<xmin>82</xmin>
			<ymin>348</ymin>
			<xmax>862</xmax>
			<ymax>1604</ymax>
		</bndbox>
	</object>
	<object>
		<name>Text</name>
		<pose>Unspecified</pose>
		<truncated>0</truncated>
		<difficult>0</difficult>
		<bndbox>
			<xmin>58</xmin>
			<ymin>1656</ymin>
			<xmax>826</xmax>
			<ymax>1780</ymax>
		</bndbox>
	</object>
	<object>
		<name>Text</name>
		<pose>Unspecified</pose>
		<truncated>0</truncated>
		<difficult>0</difficult>
		<bndbox>
			<xmin>50</xmin>
			<ymin>1792</ymin>
			<xmax>858</xmax>
			<ymax>2092</ymax>
		</bndbox>
	</object>
	<object>
		<name>Text</name>
		<pose>Unspecified</pose>
		<truncated>0</truncated>
		<difficult>0</difficult>
		<bndbox>
			<xmin>886</xmin>
			<ymin>1280</ymin>
			<xmax>2154</xmax>
			<ymax>2072</ymax>
		</bndbox>
	</object>
	<object>
		<name>Text</name>
		<pose>Unspecified</pose>
		<truncated>0</truncated>
		<difficult>0</difficult>
		<bndbox>
			<xmin>2198</xmin>
			<ymin>100</ymin>
			<xmax>2494</xmax>
			<ymax>188</ymax>
		</bndbox>
	</object>
	<object>
		<name>Text</name>
		<pose>Unspecified</pose>
		<truncated>0</truncated>
		<difficult>0</difficult>
		<bndbox>
			<xmin>2166</xmin>
			<ymin>244</ymin>
			<xmax>2618</xmax>
			<ymax>2120</ymax>
		</bndbox>
	</object>
	<object>
		<name>Text</name>
		<pose>Unspecified</pose>
		<truncated>0</truncated>
		<difficult>0</difficult>
		<bndbox>
			<xmin>2202</xmin>
			<ymin>2168</ymin>
			<xmax>2578</xmax>
			<ymax>2256</ymax>
		</bndbox>
	</object>
	<object>
		<name>Text</name>
		<pose>Unspecified</pose>
		<truncated>0</truncated>
		<difficult>0</difficult>
		<bndbox>
			<xmin>2214</xmin>
			<ymin>2268</ymin>
			<xmax>2610</xmax>
			<ymax>3208</ymax>
		</bndbox>
	</object>
	<object>
		<name>Text</name>
		<pose>Unspecified</pose>
		<truncated>0</truncated>
		<difficult>0</difficult>
		<bndbox>
			<xmin>2214</xmin>
			<ymin>3244</ymin>
			<xmax>2550</xmax>
			<ymax>3492</ymax>
		</bndbox>
	</object>
	<object>
		<name>Text</name>
		<pose>Unspecified</pose>
		<truncated>0</truncated>
		<difficult>0</difficult>
		<bndbox>
			<xmin>70</xmin>
			<ymin>2176</ymin>
			<xmax>1638</xmax>
			<ymax>2364</ymax>
		</bndbox>
	</object>
	<object>
		<name>Text</name>
		<pose>Unspecified</pose>
		<truncated>0</truncated>
		<difficult>0</difficult>
		<bndbox>
			<xmin>42</xmin>
			<ymin>2384</ymin>
			<xmax>1746</xmax>
			<ymax>3604</ymax>
		</bndbox>
	</object>
	<object>
		<name>Text</name>
		<pose>Unspecified</pose>
		<truncated>0</truncated>
		<difficult>0</difficult>
		<bndbox>
			<xmin>1722</xmin>
			<ymin>2136</ymin>
			<xmax>2166</xmax>
			<ymax>3560</ymax>
		</bndbox>
	</object>
	<object>
		<name>Figure</name>
		<pose>Unspecified</pose>
		<truncated>0</truncated>
		<difficult>0</difficult>
		<bndbox>
			<xmin>878</xmin>
			<ymin>376</ymin>
			<xmax>2118</xmax>
			<ymax>1228</ymax>
		</bndbox>
	</object>
</annotation>
