<annotation>
	<folder>UAV_data</folder>
	<filename>IMG_20231005_090314.jpg</filename>
	<source>
		<database>The UAV autolanding</database>
		<annotation>UAV AutoLanding</annotation>
		<image>flickr</image>
		<flickrid>NULL</flickrid>
	</source>
	<owner>
		<flickrid>NULL</flickrid>
		<name>ChaojieZhu</name>
	</owner>
	<size>
		<width>2736</width>
		<height>3648</height>
		<depth>3</depth>
	</size>
		<segmented>0</segmented>
	<object>
		<name>Text</name>
		<pose>Unspecified</pose>
		<truncated>0</truncated>
		<difficult>0</difficult>
		<bndbox>
			<xmin>253</xmin>
			<ymin>232</ymin>
			<xmax>2328</xmax>
			<ymax>774</ymax>
		</bndbox>
	</object>
	<object>
		<name>Text</name>
		<pose>Unspecified</pose>
		<truncated>0</truncated>
		<difficult>0</difficult>
		<bndbox>
			<xmin>958</xmin>
			<ymin>1778</ymin>
			<xmax>1678</xmax>
			<ymax>1903</ymax>
		</bndbox>
	</object>
	<object>
		<name>Text</name>
		<pose>Unspecified</pose>
		<truncated>0</truncated>
		<difficult>0</difficult>
		<bndbox>
			<xmin>212</xmin>
			<ymin>1974</ymin>
			<xmax>2483</xmax>
			<ymax>3007</ymax>
		</bndbox>
	</object>
	<object>
		<name>Text</name>
		<pose>Unspecified</pose>
		<truncated>0</truncated>
		<difficult>0</difficult>
		<bndbox>
			<xmin>224</xmin>
			<ymin>3057</ymin>
			<xmax>916</xmax>
			<ymax>3166</ymax>
		</bndbox>
	</object>
	<object>
		<name>Text</name>
		<pose>Unspecified</pose>
		<truncated>0</truncated>
		<difficult>0</difficult>
		<bndbox>
			<xmin>208</xmin>
			<ymin>3186</ymin>
			<xmax>2474</xmax>
			<ymax>3366</ymax>
		</bndbox>
	</object>
	<object>
		<name>Text</name>
		<pose>Unspecified</pose>
		<truncated>0</truncated>
		<difficult>0</difficult>
		<bndbox>
			<xmin>2520</xmin>
			<ymin>2995</ymin>
			<xmax>2641</xmax>
			<ymax>3095</ymax>
		</bndbox>
	</object>
	<object>
		<name>Text</name>
		<pose>Unspecified</pose>
		<truncated>0</truncated>
		<difficult>0</difficult>
		<bndbox>
			<xmin>2553</xmin>
			<ymin>3136</ymin>
			<xmax>2658</xmax>
			<ymax>3366</ymax>
		</bndbox>
	</object>
	<object>
		<name>Text</name>
		<pose>Unspecified</pose>
		<truncated>0</truncated>
		<difficult>0</difficult>
		<bndbox>
			<xmin>2195</xmin>
			<ymin>3407</ymin>
			<xmax>2562</xmax>
			<ymax>3512</ymax>
		</bndbox>
	</object>
	<object>
		<name>Figure</name>
		<pose>Unspecified</pose>
		<truncated>0</truncated>
		<difficult>0</difficult>
		<bndbox>
			<xmin>637</xmin>
			<ymin>762</ymin>
			<xmax>1962</xmax>
			<ymax>1712</ymax>
		</bndbox>
	</object>
</annotation>